pointy/__about__.py
pointy/__init__.py
pointy/api.py
pointy/core.py
pointy/marker.py
pointy-4.0.0.dist-info/LICENSE
pointy-4.0.0.dist-info/METADATA
pointy-4.0.0.dist-info/WHEEL
pointy-4.0.0.dist-info/top_level.txt
pointy-4.0.0.dist-info/RECORD
