Metadata-Version: 2.1
Name: pointy
Version: 4.0.0
Summary: A microscopic dependency injection library
Home-page: https://gitlab.com/brinkervii/pointy-python
Author: BrinkerVII
Author-email: brinkervii@gmail.com
License: UNKNOWN
Platform: UNKNOWN
Classifier: Development Status :: 4 - Beta
Classifier: Programming Language :: Python :: 3
Classifier: License :: OSI Approved :: Apache Software License
Classifier: Operating System :: OS Independent
Requires-Python: >=3.8
License-File: LICENSE
